hatchmat/__init__.py
hatchmat/builder.py
hatchmat/config.py
hatchmat/hook.py
hatchmat/utils.py
hatchmat-0.0.1.dist-info/METADATA
hatchmat-0.0.1.dist-info/WHEEL
hatchmat-0.0.1.dist-info/entry_points.txt
hatchmat-0.0.1.dist-info/RECORD
